kyber/__init__.py
kyber/_version.py
kyber/config.py
kyber/context.py
kyber/dash.py
kyber/deploy.py
kyber/init.py
kyber/logs.py
kyber/shell.py
kyber/status.py
kyber/utils.py
kyber/lib/__init__.py
kyber/lib/ecr.py
kyber/lib/kube.py
kyber/objects/__init__.py
kyber/objects/app.py
kyber/objects/deployment.py
kyber/objects/environment.py
kyber/objects/pod.py
kyber/objects/secret.py
kyber/templates/deployment.yaml
kyber/templates/kyber-completion.sh
kyber/templates/secret.yaml
kyber/templates/service.yaml
kyber_k8s-0.6.3.dist-info/DESCRIPTION.rst
kyber_k8s-0.6.3.dist-info/METADATA
kyber_k8s-0.6.3.dist-info/RECORD
kyber_k8s-0.6.3.dist-info/WHEEL
kyber_k8s-0.6.3.dist-info/entry_points.txt
kyber_k8s-0.6.3.dist-info/metadata.json
kyber_k8s-0.6.3.dist-info/top_level.txt
