Metadata-Version: 2.0
Name: kyber-k8s
Version: 0.6.3
Summary: Deploy and manage simple apps in kubernetes.
Home-page: https://github.com/TakumiHQ/kyber
Author: Steinn Eldjarn Sigurdarson
Author-email: steinn@takumi.com
License: UNKNOWN
Keywords: aws,kubernetes,deployments,app,paas
Platform: UNKNOWN
Requires-Dist: Jinja2 (==2.9.5)
Requires-Dist: boto3 (==1.4.4)
Requires-Dist: click (==6.7)
Requires-Dist: cmdcache (==0.1.1)
Requires-Dist: dulwich (==0.16.3)
Requires-Dist: iso8601 (==0.1.11)
Requires-Dist: pykube (==0.14.0)
Requires-Dist: sh (==1.11)
